Metadata-Version: 2.1
Name: apprentice
Version: 0.4.0
Summary: Apprentice is a library for deploying and developing actions via Dialogflow and Google Cloud Functions.
Home-page: https://github.com/andrewgy8/apprentice
Author: Andrew Graham-Yooll
Author-email: andrewgy8@gmail.com
License: GNU
Platform: UNKNOWN
Classifier: License :: OSI Approved :: GNU General Public License v3 (GPLv3)
Classifier: Programming Language :: Python
Classifier: Programming Language :: Python :: 3
Classifier: Programming Language :: Python :: 3.6
Classifier: Programming Language :: Python :: 3.7
Requires-Python: >=3.6.0
